<?xml version="1.0" encoding="UTF-8" standalone="no"?><database><movie Rating="8.5" Title="The Dark Knight Rises (2012)"/><movie Rating="8.0" Title="The Revenant (2015)"/><movie Rating="7.8" Title="Silver Linings Playbook (2012)"/><movie Rating="7.4" Title="Beauty and the Beast (2017)"/><movie Rating="7.3" Title="Monster (2003)"/><movie Rating="7.8" Title="Lost in Translation (2003)"/><movie Rating="5.3" Title="Jupiter Ascending (2015)"/><movie Rating="7.7" Title="Zombieland (2009)"/><movie Rating="6.9" Title="Step Brothers (2008)"/><movie Rating="7.0" Title="Passengers (2016)"/><movie Rating="8.1" Title="The Sixth Sense (1999)"/></database>